{
    "key": "group_62292d424c541",
    "title": "Ion Image",
    "fields": [
        {
            "key": "field_626c667c2966c",
            "label": "Image",
            "name": "image_url",
            "type": "image",
            "instructions": "",
            "required": 0,
            "conditional_logic": 0,
            "wrapper": {
                "width": "",
                "class": "",
                "id": ""
            },
            "return_format": "url",
            "preview_size": "thumbnail",
            "library": "all",
            "min_width": "",
            "min_height": "",
            "min_size": "",
            "max_width": "",
            "max_height": "",
            "max_size": "",
            "mime_types": "jpg, jpeg, png, gif"
        },
        {
            "key": "field_626c5c188499e",
            "label": "Layout",
            "name": "",
            "type": "accordion",
            "instructions": "",
            "required": 0,
            "conditional_logic": 0,
            "wrapper": {
                "width": "",
                "class": "",
                "id": ""
            },
            "open": 0,
            "multi_expand": 0,
            "endpoint": 0
        },
        {
            "key": "field_626c5ba582262",
            "label": "Margin",
            "name": "margin",
            "type": "group",
            "instructions": "",
            "required": 0,
            "conditional_logic": 0,
            "wrapper": {
                "width": "",
                "class": "",
                "id": ""
            },
            "layout": "block",
            "sub_fields": [
                {
                    "key": "field_626c5bb182263",
                    "label": "Top",
                    "name": "margin_top",
                    "type": "number",
                    "instructions": "",
                    "required": 0,
                    "conditional_logic": 0,
                    "wrapper": {
                        "width": "",
                        "class": "",
                        "id": ""
                    },
                    "default_value": 0,
                    "placeholder": "",
                    "prepend": "",
                    "append": "",
                    "min": 0,
                    "max": "",
                    "step": 1
                },
                {
                    "key": "field_626c5bd082264",
                    "label": "Right",
                    "name": "margin_right",
                    "type": "number",
                    "instructions": "",
                    "required": 0,
                    "conditional_logic": 0,
                    "wrapper": {
                        "width": "",
                        "class": "",
                        "id": ""
                    },
                    "default_value": 0,
                    "placeholder": "",
                    "prepend": "",
                    "append": "",
                    "min": 0,
                    "max": "",
                    "step": 1
                },
                {
                    "key": "field_626c5bdd82265",
                    "label": "Bottom",
                    "name": "margin_bottom",
                    "type": "number",
                    "instructions": "",
                    "required": 0,
                    "conditional_logic": 0,
                    "wrapper": {
                        "width": "",
                        "class": "",
                        "id": ""
                    },
                    "default_value": 0,
                    "placeholder": "",
                    "prepend": "",
                    "append": "",
                    "min": 0,
                    "max": "",
                    "step": 1
                },
                {
                    "key": "field_626c5bea82266",
                    "label": "Left",
                    "name": "margin_left",
                    "type": "number",
                    "instructions": "",
                    "required": 0,
                    "conditional_logic": 0,
                    "wrapper": {
                        "width": "",
                        "class": "",
                        "id": ""
                    },
                    "default_value": 0,
                    "placeholder": "",
                    "prepend": "",
                    "append": "",
                    "min": 0,
                    "max": "",
                    "step": 1
                }
            ]
        },
        {
            "key": "field_626c6c07d5e7a",
            "label": "Design",
            "name": "",
            "type": "accordion",
            "instructions": "",
            "required": 0,
            "conditional_logic": 0,
            "wrapper": {
                "width": "",
                "class": "",
                "id": ""
            },
            "open": 0,
            "multi_expand": 0,
            "endpoint": 0
        },
        {
            "key": "field_62292da5a8f5e",
            "label": "Border Radius",
            "name": "border_radius",
            "type": "range",
            "instructions": "",
            "required": 0,
            "conditional_logic": 0,
            "wrapper": {
                "width": "",
                "class": "",
                "id": ""
            },
            "default_value": 0,
            "min": "",
            "max": 50,
            "step": 10,
            "prepend": "",
            "append": ""
        },
        {
            "key": "field_62292d86a8f5d",
            "label": "Caption",
            "name": "caption",
            "type": "text",
            "instructions": "",
            "required": 0,
            "conditional_logic": 0,
            "wrapper": {
                "width": "",
                "class": "",
                "id": ""
            },
            "default_value": "",
            "placeholder": "caption",
            "prepend": "",
            "append": "",
            "maxlength": ""
        },
        {
            "key": "field_629a86f6c8dd2",
            "label": "Data",
            "name": "",
            "type": "accordion",
            "instructions": "",
            "required": 0,
            "conditional_logic": 0,
            "wrapper": {
                "width": "",
                "class": "",
                "id": ""
            },
            "open": 0,
            "multi_expand": 0,
            "endpoint": 0
        },
        {
            "key": "field_629a86ffc8dd3",
            "label": "Token",
            "name": "token",
            "type": "text",
            "instructions": "Data token entered here will replace the src attribute of the image element.",
            "required": 0,
            "conditional_logic": 0,
            "wrapper": {
                "width": "",
                "class": "",
                "id": ""
            },
            "default_value": "",
            "placeholder": "",
            "prepend": "",
            "append": "",
            "maxlength": ""
        }
    ],
    "location": [
        [
            {
                "param": "block",
                "operator": "==",
                "value": "acf\/ion-image"
            }
        ]
    ],
    "menu_order": 0,
    "position": "normal",
    "style": "default",
    "label_placement": "top",
    "instruction_placement": "label",
    "hide_on_screen": "",
    "active": true,
    "description": "",
    "show_in_rest": 0,
    "modified": 1655914800
}